hda/__init__.py
hda/api.py
hda/utils.py
hda-2.34.dist-info/licenses/LICENSE.txt
hda-2.34.dist-info/METADATA
hda-2.34.dist-info/WHEEL
hda-2.34.dist-info/top_level.txt
hda-2.34.dist-info/zip-safe
hda-2.34.dist-info/RECORD
