Metadata-Version: 2.4
Name: hda
Version: 2.34
Summary: API to harmonised data access for DIAS/WEkEO.
Home-page: https://github.com/ecmwf/hda
Author: ECMWF
Author-email: ECMWF <software.support@ecmwf.int>
License: 
Project-URL: Homepage, https://github.com/ecmwf/hda
Keywords: API,data access,DIAS,WEkEO
Classifier: Development Status :: 5 - Production/Stable
Classifier: Intended Audience :: Developers
Classifier: License :: OSI Approved :: Apache Software License
Classifier: Programming Language :: Python :: 3
Classifier: Programming Language :: Python :: 3.6
Classifier: Programming Language :: Python :: 3.7
Classifier: Programming Language :: Python :: 3.8
Classifier: Programming Language :: Python :: 3.9
Classifier: Programming Language :: Python :: 3.10
Classifier: Programming Language :: Python :: 3.11
Classifier: Programming Language :: Python :: 3.12
Classifier: Topic :: Software Development :: Libraries :: Python Modules
Requires-Python: >=3.6
License-File: LICENSE.txt
Requires-Dist: requests>=2.5.0
Requires-Dist: tqdm
Dynamic: author
Dynamic: home-page
Dynamic: license-file
